{
    "problem_index": 1168,
    "final_answer": "11",
    "duration_seconds": 91.49503111839294,
    "full_history": [
        {
            "turn": 0,
            "attempt": 0,
            "model": "draft",
            "output": "Alright, let me try to work through this problem step by step. The equation given is \\( z^4 + 4z^3i - 6z^2 - 4zi - i = 0 \\). It says that the solutions are vertices of a convex polygon in the complex plane, and we need to find the area of that polygon expressed in a specific form and then find \\( a + b + p \\).\n\nFirst, I remember that sometimes complex polynomial equations can be factored using substitution. Maybe if I let \\( w = z + i \\) or something similar, the equation might simplify. Let me try substituting \\( z = w - i \\) to see if that helps.\n\nSo, substituting \\( z = w - i \\):\n\n\\( (w - i)^4 + 4(w - i)^3i - 6(w - i)^2 - 4(w - i)i - i = 0 \\)\n\nThis looks complicated, but maybe it can be expanded and simplified. Let's expand each term one by one.\n\nFirst term: \\( (w - i)^4 \\)\n\nUsing the binomial theorem:\n\n\\( (w - i)^4 = w^4 - 4w^3i + 6w^2i^2 - 4wi^3 + i^4 \\)\nSimplify the powers of i:\n\\( i^2 = -1, i^3 = -i, i^4 = 1 \\)\nSo,\n\\( w^4 - 4w^3i + 6w^2(-1) - 4w(-i) + 1 \\)\nWhich is:\n\\( w^4 - 4iw^3 - 6w^2 + 4iw + 1 \\)\n\nSecond term: \\( 4(w - i)^3i \\)\nFirst, expand \\( (w - i)^3 \\):\n\\( (w - i)^3 = w^3 - 3w^2i + 3wi^2 - i^3 \\)\nSimplify:\n\\( w^3 - 3w^2i + 3w(-1) - (-i) \\) since \\( i^3 = -i \\)\nSo, \\( w^3 - 3iw^2 - 3w + i \\)\nNow multiply by 4i:\n\\( 4i(w^3 - 3iw^2 - ",
            "ppl": 1.1893061718608677,
            "percentile": 0.84125,
            "accepted": false
        },
        {
            "turn": 0,
            "attempt": 1,
            "model": "draft",
            "output": "Alright, so I have this equation: \\( z^4 + 4z^3i - 6z^2 - 4zi - i = 0 \\). The solutions to this equation are the vertices of a convex polygon in the complex plane, and I need to find the area of that polygon. The area is supposed to be expressible in the form \\( p^{a/b} \\), where \\( p \\) is prime, and \\( a \\) and \\( b \\) are coprime. Then, I have to find \\( a + b + p \\).\n\nHmm, okay. Let me start by trying to factor this equation. It's a quartic equation, which can be tricky, but maybe it's a biquadratic or can be factored into quadratics. Let me see.\n\nLooking at the equation: \\( z^4 + 4z^3i - 6z^2 - 4zi - i = 0 \\). The coefficients involve powers of \\( i \\), which suggests that maybe a substitution involving \\( i \\) could help. Let me try substituting \\( w = iz \\) or something like that.\n\nWait, another thought: sometimes equations with complex coefficients can be transformed into polynomials with real coefficients by substituting \\( z = x + yi \\). But that might get messy because of the cross terms. Alternatively, maybe this equation is related to a known polynomial form.\n\nWait, let me check if this equation is a transformed version of a known polynomial. Let me see the coefficients: 1, 4i, -6, -4i, -i. Hmm, that seems similar to the expansion of something like \\( (z + i)^4 \\), but let me check.\n\nCalculating \\( (z + i)^4 \\):\nFirst, \\( (z + i)^2 = z^2 + 2zi + i^2 = z^2 + 2zi - 1 \\).\nThen, \\( (z + i)^4 = (z^2 + 2zi - 1)^2 = z^4 + 4z^3i + (4z^2i^2 + 4z^2) + ... \\). Wait, maybe I should compute it step by step.\n\nWait, actually, let me compute \\( (z + i)^4 \\):\nFirst, \\( (z + i)^2 = z^2 + 2",
            "ppl": 1.2375975670734376,
            "percentile": 0.943125,
            "accepted": false
        },
        {
            "turn": 0,
            "attempt": 2,
            "model": "draft",
            "output": "Okay, so I have this equation: \\( z^4 + 4z^3i - 6z^2 - 4zi - i = 0 \\). The solutions to this equation are the vertices of a convex polygon in the complex plane, and I need to find the area of that polygon. The area is supposed to be expressible in the form \\( p^{a/b} \\), where \\( p \\) is prime, \\( a \\) and \\( b \\) are coprime, and then find \\( a + b + p \\).\n\nHmm, first, I remember that complex equations like this can often be solved by factoring or by using substitution. The equation is a quartic, which is a fourth-degree polynomial. Maybe I can factor it into quadratics or something.\n\nLooking at the equation: \\( z^4 + 4z^3i - 6z^2 - 4zi - i = 0 \\). The coefficients involve powers of \\( i \\), which suggests that maybe a substitution could simplify things. Let me think about substituting \\( w = z + c \\) for some constant \\( c \\) to eliminate certain terms.\n\nAlternatively, I notice that the coefficients have a pattern: 1, 4i, -6, -4i, -i. That seems similar to the expansion of something like \\( (z + i)^4 \\), but let me check.\n\nWait, \\( (z + i)^4 \\) would be \\( z^4 + 4z^3i + 6z^2i^2 + 4zi^3 + i^4 \\). Calculating that: \\( z^4 + 4z^3i - 6z^2 - 4zi + 1 \\). Hmm, that's similar but not exactly the same as our equation. The original equation is \\( z^4 + 4z^3i - 6z^2 - 4zi - i = 0 \\). So, if I subtract \\( (z + i)^4 \\) from our equation, I get:\n\n\\( (z^4 + 4z^3i - 6z^2 - 4zi - i) - (z^4 + 4z^3i - 6z^2 - 4zi + 1) = 0 - 0 \\)\n\nSimplifying that: \\(",
            "ppl": 1.177954249304378,
            "percentile": 0.805,
            "accepted": false
        },
        {
            "turn": 1,
            "attempt": 0,
            "model": "draft",
            "output": " 0z^4 + 0z^3i + 0z^2 + 0zi - i - 1 = 0 \\), so \\( -i - 1 = 0 \\), which is not true. So that approach doesn't help.\n\nWait, maybe I can factor the original equation as \\( (z^2 + az + b)(z^2 + cz + d) \\). Let me try that.\n\nAssume \\( z^4 + 4z^3i - 6z^2 - 4zi - i = (z^2 + az + b)(z^2 + cz + d) \\).\n\nMultiplying out the right side: \\( z^4 + (a + c)z^3 + (ac + b + d)z^2 + (ad + bc)z + bd \\).\n\nSet this equal to the original equation:\n\n1. Coefficient of \\( z^4 \\): 1 = 1, which is fine.\n2. Coefficient of \\( z^3 \\): \\( a + c = 4i \\).\n3. Coefficient of \\( z^2 \\): \\( ac + b + d = -6 \\).\n4. Coefficient of \\( z \\): \\( ad + bc = -4i \\).\n5. Constant term: \\( bd = -i \\).\n\nSo, we have a system of equations:\n\n1. \\( a + c = 4i \\)\n2. \\( ac + b + d = -6 \\)\n3. \\( ad + bc = -4i \\)\n4. \\( bd = -i \\)\n\nWe need to solve for \\( a, b, c, d \\). Let me see if I can find integers or complex numbers that satisfy these.\n\nLooking at equation 4: \\( bd = -i \\). So, possible pairs for \\( b \\) and \\( d \\) could be \\( (1, -i) \\), \\( (-1, i) \\), \\( (i, 1) \\), \\( (-i, -1) \\), etc. Let me try \\( b = 1 \\) and \\( d = -i \\).\n\nThen, equation 4 is satisfied: \\( 1 * (-i) = -i \\).\n\nNow, equation 1: \\( a + c = 4i \\).\n\nEquation 2: \\( ac + 1 + (-i)",
            "ppl": 1.1436280805269434,
            "percentile": 0.643125,
            "accepted": false
        },
        {
            "turn": 1,
            "attempt": 1,
            "model": "draft",
            "output": " 0z^4 + 0z^3i + 0z^2 + 0zi - i - 1 = 0 \\), so \\( -i - 1 = 0 \\), which is not true. So that approach doesn't help.\n\nWait, maybe I can factor the original equation as \\( (z^2 + az + b)(z^2 + cz + d) \\). Let me try that.\n\nExpanding \\( (z^2 + az + b)(z^2 + cz + d) \\) gives \\( z^4 + (a + c)z^3 + (ac + b + d)z^2 + (ad + bc)z + bd \\).\n\nComparing coefficients with the original equation:\n\n1. Coefficient of \\( z^4 \\): 1, which matches.\n2. Coefficient of \\( z^3 \\): \\( a + c = 4i \\).\n3. Coefficient of \\( z^2 \\): \\( ac + b + d = -6 \\).\n4. Coefficient of \\( z \\): \\( ad + bc = -4i \\).\n5. Constant term: \\( bd = -i \\).\n\nSo, I have a system of equations:\n\n1. \\( a + c = 4i \\)\n2. \\( ac + b + d = -6 \\)\n3. \\( ad + bc = -4i \\)\n4. \\( bd = -i \\)\n\nI need to solve for \\( a, b, c, d \\). Let me assume that \\( a \\) and \\( c \\) are complex numbers, as are \\( b \\) and \\( d \\).\n\nLooking at equation 4: \\( bd = -i \\). So, \\( b \\) and \\( d \\) are factors of \\( -i \\). Let me think about possible pairs for \\( b \\) and \\( d \\). Since \\( -i = (-i) \\times 1 \\) or \\( 1 \\times (-i) \\), or maybe other factors, but since \\( i \\) is a prime in the Gaussian integers, the only factors are units times powers of \\( i \\). So, possible pairs for \\( b \\) and \\( d \\) could be \\( (1, -i) \\), \\( (-1, i) \\), \\( (i, 1) \\), \\( (-i, -1) \\",
            "ppl": 1.1680869446878954,
            "percentile": 0.759375,
            "accepted": false
        },
        {
            "turn": 1,
            "attempt": 2,
            "model": "draft",
            "output": " (0) + (0) + (0) + (0) + (-i - 1) = - (i + 1) = 0 \\). Wait, that doesn't make sense. So, maybe that substitution isn't directly helpful.\n\nAlternatively, perhaps I can factor the equation as a quadratic in \\( z^2 \\) or something else. Let me try grouping terms.\n\nLooking at the equation: \\( z^4 + 4z^3i - 6z^2 - 4zi - i = 0 \\). Let me group the terms as \\( (z^4 + 4z^3i) + (-6z^2 - 4zi) - i = 0 \\).\n\nFactor out \\( z^3 \\) from the first group: \\( z^3(z + 4i) \\). From the second group, factor out \\( -2z \\): \\( -2z(3z + 2i) \\). So, the equation becomes:\n\n\\( z^3(z + 4i) - 2z(3z + 2i) - i = 0 \\).\n\nHmm, not sure if that helps. Maybe another approach.\n\nWait, perhaps the equation can be written as \\( (z^2 + 2iz + a)(z^2 + bz + c) = 0 \\). Let me try to factor it into two quadratics.\n\nExpanding \\( (z^2 + 2iz + a)(z^2 + bz + c) \\):\n\n= \\( z^4 + (b + 2i)z^3 + (c + 2i b + a)z^2 + (2i c + a b)z + a c \\).\n\nComparing coefficients with the original equation:\n\nOriginal: \\( z^4 + 4i z^3 -6 z^2 -4i z -i \\).\n\nSo, set up equations:\n\n1. Coefficient of \\( z^4 \\): 1 = 1 (okay)\n2. Coefficient of \\( z^3 \\): \\( b + 2i = 4i \\) => \\( b = 4i - 2i = 2i \\)\n3. Coefficient of \\( z^2 \\): \\( c + 2i b + a = -6 \\)\n4. Coefficient of \\( z \\): \\( 2",
            "ppl": 1.1661165437118823,
            "percentile": 0.756875,
            "accepted": false
        },
        {
            "turn": 2,
            "attempt": 0,
            "model": "draft",
            "output": " = -6 \\) => \\( ac - i = -6 \\) => \\( ac = -6 + i \\).\n\nEquation 3: \\( a*(-i) + c*1 = -4i \\) => \\( -ai + c = -4i \\).\n\nSo, from equation 1: \\( c = 4i - a \\).\n\nSubstitute into equation 3: \\( -ai + (4i - a) = -4i \\).\n\nSimplify: \\( -ai + 4i - a = -4i \\).\n\nGroup like terms: \\( (-a)i + 4i - a = -4i \\).\n\nFactor out \\( i \\): \\( i(-a + 4) - a = -4i \\).\n\nSo, \\( i(4 - a) - a = -4i \\).\n\nLet me write this as: \\( (4 - a)i - a = -4i \\).\n\nComparing real and imaginary parts:\n\nReal part: \\( -a = 0 \\) => \\( a = 0 \\).\n\nImaginary part: \\( (4 - a) = -4 \\) => \\( 4 - a = -4 \\) => \\( -a = -8 \\) => \\( a = 8 \\).\n\nWait, that's a contradiction. If \\( a = 0 \\) from the real part, but \\( a = 8 \\) from the imaginary part. So, this choice of \\( b = 1 \\), \\( d = -i \\) doesn't work.\n\nLet me try another pair for \\( b \\) and \\( d \\). Maybe \\( b = i \\), \\( d = -1 \\).\n\nThen, equation 4: \\( i*(-1) = -i \\), which works.\n\nEquation 1: \\( a + c = 4i \\).\n\nEquation 2: \\( ac + i + (-1) = -6 \\) => \\( ac + i - 1 = -6 \\) => \\( ac = -5 - i \\).\n\nEquation 3: \\( a*(-1) + c*i = -4i \\) => \\( -a + ci = -4i \\).\n\nFrom equation 1: \\( c = 4i - a \\).\n\nSubstitute into equation 3: \\( -a + (4i - a)i = -4i \\).\n\nSimplify: \\( -a +",
            "ppl": 1.1229805391065335,
            "percentile": 0.486875,
            "accepted": true
        },
        {
            "turn": 3,
            "attempt": 0,
            "model": "draft",
            "output": " 4i^2 - a i = -4i \\).\n\nSince \\( i^2 = -1 \\), this becomes \\( -a -1 - a i = -4i \\).\n\nGrouping terms: \\( (-a -1) + (-a)i = -4i \\).\n\nSo, real part: \\( -a -1 = 0 \\) => \\( a = -1 \\).\n\nImaginary part: \\( -a = -4 \\) => \\( a = 4 \\).\n\nAgain, a contradiction. \\( a = -1 \\) vs. \\( a = 4 \\). So, this doesn't work either.\n\nHmm, maybe try \\( b = -1 \\), \\( d = i \\).\n\nThen, equation 4: \\( (-1)(i) = -i \\), which works.\n\nEquation 1: \\( a + c = 4i \\).\n\nEquation 2: \\( ac + (-1) + i = -6 \\) => \\( ac -1 + i = -6 \\) => \\( ac = -5 - i \\).\n\nEquation 3: \\( a*(i) + c*(-1) = -4i \\) => \\( ai - c = -4i \\).\n\nFrom equation 1: \\( c = 4i - a \\).\n\nSubstitute into equation 3: \\( ai - (4i - a) = -4i \\).\n\nSimplify: \\( ai -4i + a = -4i \\).\n\nGroup terms: \\( a + (a)i -4i = -4i \\).\n\nFactor: \\( a(1 + i) -4i = -4i \\).\n\nSo, \\( a(1 + i) = 0 \\).\n\nSince \\( 1 + i \\) is not zero, \\( a = 0 \\).\n\nThen, from equation 1: \\( c = 4i - 0 = 4i \\).\n\nCheck equation 2: \\( ac = 0 * 4i = 0 \\). But equation 2 requires \\( ac = -5 - i \\). So, 0 \u2260 -5 -i. Doesn't work.\n\nHmm, maybe try \\( b = -i \\), \\( d = 1 \\).\n\nEquation 4: \\( (-i)(1) = -i \\), which works.\n\nEquation 1: \\( a + c = 4i \\).\n\n",
            "ppl": 1.1000883477527759,
            "percentile": 0.32375,
            "accepted": true
        },
        {
            "turn": 4,
            "attempt": 0,
            "model": "draft",
            "output": "Equation 2: \\( ac + (-i) + 1 = -6 \\) => \\( ac -i +1 = -6 \\) => \\( ac = -5 + i \\).\n\nEquation 3: \\( a*(1) + c*(-i) = -4i \\) => \\( a - ci = -4i \\).\n\nFrom equation 1: \\( c = 4i - a \\).\n\nSubstitute into equation 3: \\( a - (4i - a)i = -4i \\).\n\nSimplify: \\( a -4i^2 + a i = -4i \\).\n\nSince \\( i^2 = -1 \\), this becomes \\( a - (-1) + a i = -4i \\) => \\( a +1 + a i = -4i \\).\n\nGroup terms: \\( (a +1) + a i = -4i \\).\n\nSo, real part: \\( a +1 = 0 \\) => \\( a = -1 \\).\n\nImaginary part: \\( a = -4 \\).\n\nAgain, a contradiction. \\( a = -1 \\) vs. \\( a = -4 \\). Doesn't work.\n\nHmm, maybe my initial assumption is wrong. Maybe the quartic factors into two quadratics with complex coefficients, not necessarily real or integer coefficients. Alternatively, perhaps a substitution can help.\n\nWait, another approach: Let me try substituting \\( w = z + k \\) for some constant \\( k \\) to make the equation a biquadratic or something.\n\nLooking at the equation: \\( z^4 + 4i z^3 -6 z^2 -4i z -i = 0 \\).\n\nLet me try \\( w = z + c \\). Maybe \\( c = i \\) or something.\n\nLet me compute \\( (z + i)^4 \\) as before:\n\n\\( (z + i)^4 = z^4 + 4i z^3 -6 z^2 -4i z +1 \\).\n\nSo, if I subtract this from the original equation:\n\nOriginal equation: \\( z^4 +4i z^3 -6 z^2 -4i z -i =0 \\).\n\nSubtract \\( (z + i)^4 \\): \\( (z^4 +4i z^3 -6 z^2 -4i z +1) \\).\n\nSo, subtracting gives:\n\n",
            "ppl": 1.1850078544264415,
            "percentile": 0.82625,
            "accepted": false
        },
        {
            "turn": 4,
            "attempt": 1,
            "model": "draft",
            "output": "Equation 2: \\( ac + (-i) + 1 = -6 \\) => \\( ac -i +1 = -6 \\) => \\( ac = -5 + i \\).\n\nEquation 3: \\( a*(1) + c*(-i) = -4i \\) => \\( a - ci = -4i \\).\n\nFrom equation 1: \\( c = 4i - a \\).\n\nSubstitute into equation 3: \\( a - (4i - a)(-i) = -4i \\).\n\nSimplify: \\( a - [ -4i^2 + a i ] = -4i \\).\n\nSince \\( i^2 = -1 \\), this becomes \\( a - [4 + a i ] = -4i \\).\n\nSo, \\( a -4 - a i = -4i \\).\n\nGroup terms: \\( (a -4) + (-a)i = -4i \\).\n\nReal part: \\( a -4 = 0 \\) => \\( a = 4 \\).\n\nImaginary part: \\( -a = -4 \\) => \\( a = 4 \\).\n\nSo, both parts give \\( a = 4 \\). Then, \\( c = 4i - 4 = 4(i - 1) \\).\n\nCheck equation 2: \\( ac = 4 * 4(i - 1) = 16(i - 1) = 16i -16 \\). But equation 2 requires \\( ac = -5 + i \\). So, 16i -16 \u2260 -5 +i. Doesn't work.\n\nHmm, maybe I need a different approach. Maybe the quartic can be transformed into a biquadratic equation or something else.\n\nWait, another thought: the equation resembles a quadratic in \\( z^2 \\), but with cross terms. Let me see.\n\nAlternatively, maybe substitute \\( w = z + k \\) for some \\( k \\) to eliminate the cubic term. Let me try that.\n\nLet \\( w = z + k \\). Then, \\( z = w - k \\). Substitute into the equation:\n\n\\( (w - k)^4 + 4(w - k)^3 i -6(w - k)^2 -4(w - k)i -i = 0 \\).\n\nThis might get messy, but let's try expanding.\n\nFirst, expand \\( (w - k)^4 \\):\n\n\\(",
            "ppl": 1.1691338199575914,
            "percentile": 0.763125,
            "accepted": false
        },
        {
            "turn": 4,
            "attempt": 2,
            "model": "draft",
            "output": "Equation 2: \\( ac + (-i) + 1 = -6 \\) => \\( ac -i +1 = -6 \\) => \\( ac = -5 + i \\).\n\nEquation 3: \\( a*(1) + c*(-i) = -4i \\) => \\( a - ci = -4i \\).\n\nFrom equation 1: \\( c = 4i - a \\).\n\nSubstitute into equation 3: \\( a - (4i - a)i = -4i \\).\n\nSimplify: \\( a -4i^2 + a i = -4i \\).\n\nSince \\( i^2 = -1 \\), this becomes \\( a - (-1) + a i = -4i \\) => \\( a +1 + a i = -4i \\).\n\nGroup terms: \\( (a +1) + a i = -4i \\).\n\nSo, real part: \\( a +1 = 0 \\) => \\( a = -1 \\).\n\nImaginary part: \\( a = -4 \\).\n\nAgain, a contradiction. \\( a = -1 \\) vs. \\( a = -4 \\). Doesn't work.\n\nHmm, maybe my initial assumption is wrong. Maybe the quartic factors into two quadratics with complex coefficients, not necessarily real or integer coefficients. Alternatively, perhaps a substitution can help.\n\nWait, another approach: Let me try substituting \\( w = z + k \\) for some constant \\( k \\) to eliminate the cubic term. The cubic term is \\( 4z^3i \\). If I can make the coefficient of \\( w^3 \\) zero, that might help.\n\nLet me set \\( w = z + k \\). Then, \\( z = w - k \\).\n\nSubstitute into the equation:\n\n\\( (w - k)^4 + 4i(w - k)^3 -6(w - k)^2 -4i(w - k) -i = 0 \\).\n\nExpanding each term:\n\nFirst, \\( (w - k)^4 = w^4 - 4k w^3 + 6k^2 w^2 -4k^3 w + k^4 \\).\n\nSecond, \\( 4i(w - k)^3 = 4i(w^3 - 3k w^2 + 3k^2 w -k^3) = 4i w^",
            "ppl": 1.1489798145472752,
            "percentile": 0.66625,
            "accepted": false
        },
        {
            "turn": 5,
            "attempt": 0,
            "model": "draft",
            "output": "3 -12i k w^2 +12i k^2 w -4i k^3 \\).\n\nThird, \\( -6(w - k)^2 = -6(w^2 - 2k w + k^2) = -6w^2 +12k w -6k^2 \\).\n\nFourth, \\( -4i(w - k) = -4i w +4i k \\).\n\nFifth, the constant term: \\( -i \\).\n\nNow, combine all these:\n\n1. \\( w^4 -4k w^3 +6k^2 w^2 -4k^3 w +k^4 \\)\n2. \\( +4i w^3 -12i k w^2 +12i k^2 w -4i k^3 \\)\n3. \\( -6w^2 +12k w -6k^2 \\)\n4. \\( -4i w +4i k \\)\n5. \\( -i \\)\n\nNow, combine like terms:\n\n- \\( w^4 \\): 1 term, coefficient 1.\n- \\( w^3 \\): -4k +4i. So coefficient: (-4k +4i).\n- \\( w^2 \\): 6k^2 -12i k -6. Coefficient: 6k^2 -12i k -6.\n- \\( w \\): -4k^3 +12i k^2 +12k -4i. Coefficient: -4k^3 +12i k^2 +12k -4i.\n- Constants: k^4 -4i k^3 -6k^2 +4i k -i.\n\nWe want to eliminate the \\( w^3 \\) term. So set coefficient of \\( w^3 \\) to zero:\n\n-4k +4i = 0 => -4k = -4i => k = i.\n\nSo, set \\( k = i \\). Let's substitute \\( k = i \\) into the other coefficients.\n\nCompute each coefficient:\n\n1. \\( w^4 \\): 1.\n2. \\( w^3 \\): 0 (as desired).\n3. \\( w^2 \\): 6(i)^2 -12i(i) -6 = 6(-1) -12i^2 -6 = -6 - (-12) -6 = -6 +",
            "ppl": 1.0854764599306772,
            "percentile": 0.2375,
            "accepted": true
        },
        {
            "turn": 6,
            "attempt": 0,
            "model": "draft",
            "output": "12 -6 = 0.\n4. \\( w \\): -4(i)^3 +12i(i)^2 +12(i) -4i = -4(-i) +12i(-1) +12i -4i = 4i -12i +12i -4i = 0.\n5. Constants: (i)^4 -4i(i)^3 -6(i)^2 +4i(i) -i = 1 -4i(-i) -6(-1) +4i^2 -i.\n\nSimplify constants:\n\n1. \\( (i)^4 = 1 \\).\n2. \\( -4i(i)^3 = -4i(-i) = 4i^2 = 4(-1) = -4 \\).\n3. \\( -6(i)^2 = -6(-1) = 6 \\).\n4. \\( 4i(i) = 4i^2 = -4 \\).\n5. \\( -i \\).\n\nSo, constants: 1 -4 +6 -4 -i = (1 -4 +6 -4) -i = (-1) -i.\n\nSo, after substitution, the equation becomes:\n\n\\( w^4 + 0w^3 + 0w^2 + 0w + (-1 -i) = 0 \\).\n\nSo, \\( w^4 -1 -i = 0 \\) => \\( w^4 = 1 + i \\).\n\nSo, the equation reduces to \\( w^4 = 1 + i \\). Therefore, the solutions for \\( w \\) are the fourth roots of \\( 1 + i \\).\n\nSo, \\( w = \\sqrt[4]{1 + i} \\). To find the fourth roots, we can express \\( 1 + i \\) in polar form.\n\nExpress \\( 1 + i \\) in polar form: \\( 1 + i = \\sqrt{2} e^{i\\pi/4} \\).\n\nTherefore, the fourth roots are given by \\( w = (\\sqrt{2})^{1/4} e^{i(\\pi/16 + k\\pi/2)} \\) for \\( k = 0, 1, 2, 3 \\).\n\nCompute \\( (\\sqrt{2})^{1/4} = (2^{1/2})^{1/4} = 2^{1/",
            "ppl": 1.0952785415456823,
            "percentile": 0.308125,
            "accepted": true
        },
        {
            "turn": 7,
            "attempt": 0,
            "model": "draft",
            "output": "8} \\).\n\nSo, the four roots are:\n\n\\( w_k = 2^{1/8} e^{i(\\pi/16 + k\\pi/2)} \\) for \\( k = 0, 1, 2, 3 \\).\n\nBut remember that \\( w = z + i \\), so \\( z = w - i \\).\n\nTherefore, the solutions for \\( z \\) are:\n\n\\( z_k = 2^{1/8} e^{i(\\pi/16 + k\\pi/2)} - i \\).\n\nSo, we have four points in the complex plane, each of the form \\( z_k = 2^{1/8} e^{i\\theta_k} - i \\), where \\( \\theta_k = \\pi/16 + k\\pi/2 \\).\n\nNow, to find the area of the convex polygon formed by these four points.\n\nFirst, let's note that these four points are the fourth roots of \\( 1 + i \\), shifted by \\( -i \\). So, they form a regular quadrilateral (a square) in the complex plane, but scaled and rotated.\n\nWait, but are they a regular quadrilateral? Since the roots of \\( w^4 = 1 + i \\) are equally spaced around a circle, but the circle has radius \\( 2^{1/8} \\). So, the four points \\( w_k \\) form a regular quadrilateral (a square) on the circle of radius \\( 2^{1/8} \\).\n\nBut then, when we subtract \\( i \\), we are translating each point by \\( -i \\). So, the shape remains a square, but its center is shifted.\n\nWait, but the area of the polygon is the area of the square, regardless of the translation. So, the area depends only on the radius of the circle on which the points lie.\n\nThe radius is \\( 2^{1/8} \\). The side length of the square inscribed in a circle of radius \\( r \\) is \\( s = \\sqrt{2} r \\). Wait, no, actually, for a square inscribed in a circle of radius \\( r \\), the diagonal is \\( 2r \\). The diagonal of a square is \\( s\\sqrt{2} \\), so \\( s\\sqrt{2} = 2r \\) => \\( s = \\sqrt{2} r",
            "ppl": 1.2631451976800523,
            "percentile": 0.9625,
            "accepted": false
        },
        {
            "turn": 7,
            "attempt": 1,
            "model": "draft",
            "output": "8} \\).\n\nSo, the four roots are:\n\n\\( w_k = 2^{1/8} e^{i(\\pi/16 + k\\pi/2)} \\) for \\( k = 0, 1, 2, 3 \\).\n\nBut remember that \\( w = z + i \\), so \\( z = w - i \\).\n\nTherefore, the solutions for \\( z \\) are:\n\n\\( z_k = 2^{1/8} e^{i(\\pi/16 + k\\pi/2)} - i \\).\n\nSo, we have four points in the complex plane, each of the form \\( z_k = 2^{1/8} e^{i\\theta_k} - i \\), where \\( \\theta_k = \\pi/16 + k\\pi/2 \\).\n\nNow, to find the area of the convex polygon formed by these four points.\n\nFirst, let's note that these four points are the fourth roots of \\( 1 + i \\), shifted by \\( -i \\). So, they form a regular quadrilateral (a square) in the complex plane, but scaled and rotated.\n\nWait, but are they forming a square? Let me think.\n\nThe fourth roots of a complex number are equally spaced around a circle, so if we have four roots, they should form a regular quadrilateral, which is a square. However, since we have a shift by \\( -i \\), the square is not centered at the origin but shifted down by \\( i \\).\n\nBut regardless, the shape is a square, just translated. The area of a square is side length squared. So, if I can find the distance between consecutive roots, that would be the side length.\n\nAlternatively, since all roots lie on a circle of radius \\( 2^{1/8} \\), the distance between consecutive roots is \\( 2 \\times 2^{1/8} \\times \\sin(\\pi/4) \\).\n\nWait, the chord length between two points on a circle of radius \\( r \\) separated by angle \\( \\theta \\) is \\( 2r \\sin(\\theta/2) \\). Here, the angle between consecutive roots is \\( \\pi/2 \\), so chord length is \\( 2r \\sin(\\pi/4) = 2r \\times \\sqrt{2}/2 = r \\sqrt{2} \\).\n\nGiven \\( r = 2^{",
            "ppl": 1.2330170377377103,
            "percentile": 0.93125,
            "accepted": false
        },
        {
            "turn": 7,
            "attempt": 2,
            "model": "draft",
            "output": "8} \\).\n\nSo, the four roots are:\n\n\\( w_k = 2^{1/8} e^{i(\\pi/16 + k\\pi/2)} \\) for \\( k = 0, 1, 2, 3 \\).\n\nBut remember that \\( w = z + i \\), so \\( z = w - i \\).\n\nTherefore, the solutions for \\( z \\) are:\n\n\\( z_k = 2^{1/8} e^{i(\\pi/16 + k\\pi/2)} - i \\).\n\nSo, we have four points in the complex plane, each of the form \\( z_k = 2^{1/8} e^{i\\theta_k} - i \\), where \\( \\theta_k = \\pi/16 + k\\pi/2 \\).\n\nNow, to find the area of the convex polygon formed by these four points.\n\nFirst, let's note that these four points are the fourth roots of \\( 1 + i \\), shifted by \\( -i \\). So, they form a regular quadrilateral (a square) in the complex plane, but scaled and rotated.\n\nWait, but are they forming a square? Let me think.\n\nThe fourth roots of a complex number are equally spaced around a circle, so if we have four roots, they should form a regular quadrilateral, which is a square. However, since we have a shift by \\( -i \\), the square is not centered at the origin but shifted down by \\( i \\).\n\nBut regardless, the shape is a square, just translated. The area of a square is side length squared. So, if I can find the distance between consecutive roots, that would be the side length.\n\nAlternatively, since all roots lie on a circle of radius \\( 2^{1/8} \\), the distance between consecutive roots is \\( 2 \\times 2^{1/8} \\times \\sin(\\pi/4) \\).\n\nWait, the chord length between two points on a circle of radius \\( r \\) separated by angle \\( \\theta \\) is \\( 2r \\sin(\\theta/2) \\). Here, the angle between consecutive roots is \\( \\pi/2 \\), so chord length is \\( 2r \\sin(\\pi/4) = 2r \\times \\sqrt{2}/2 = r \\sqrt{2} \\).\n\nGiven \\( r = 2^{",
            "ppl": 1.2330170377377103,
            "percentile": 0.93125,
            "accepted": false
        },
        {
            "turn": 8,
            "attempt": 0,
            "model": "draft",
            "output": "1/8} \\), so chord length is \\( 2^{1/8} \\times \\sqrt{2} = 2^{1/8} \\times 2^{1/2} = 2^{5/8} \\).\n\nTherefore, the side length of the square is \\( 2^{5/8} \\), so the area is \\( (2^{5/8})^2 = 2^{5/4} = 2^{1 + 1/4} = 2 \\times 2^{1/4} = 2^{5/4} \\).\n\nWait, but hold on. The four points are on a circle of radius \\( 2^{1/8} \\), but after shifting by \\( -i \\), does that affect the distances? Because shifting doesn't change distances between points, only their positions. So, the polygon remains a square with side length \\( 2^{5/8} \\), so area \\( 2^{5/4} \\).\n\nBut wait, let me double-check. The chord length is \\( 2r \\sin(\\theta/2) \\). Here, \\( \\theta = \\pi/2 \\), so chord length is \\( 2 * 2^{1/8} * \\sin(\\pi/4) = 2 * 2^{1/8} * \\sqrt{2}/2 = 2^{1/8} * \\sqrt{2} = 2^{1/8 + 1/2} = 2^{5/8} \\). So, yes, chord length is \\( 2^{5/8} \\), so side length is \\( 2^{5/8} \\), area is \\( (2^{5/8})^2 = 2^{5/4} \\).\n\nBut wait, 2^{5/4} is equal to \\( \\sqrt[4]{32} \\), since \\( 32 = 2^5 \\). So, \\( 2^{5/4} = (2^{1/4})^5 \\). Hmm, but the problem says the area can be expressed as \\( p^{a/b} \\), where \\( p \\) is prime. Here, \\( p = 2 \\), \\( a = 5 \\), \\( b = 4 \\). Are 5 and 4 coprime? Yes, since ",
            "ppl": 1.1714854983567684,
            "percentile": 0.7725,
            "accepted": false
        },
        {
            "turn": 8,
            "attempt": 1,
            "model": "draft",
            "output": "1/8} \\), so chord length is \\( 2^{1/8} \\times \\sqrt{2} = 2^{1/8} \\times 2^{1/2} = 2^{5/8} \\).\n\nTherefore, the side length of the square is \\( 2^{5/8} \\), so the area is \\( (2^{5/8})^2 = 2^{5/4} = 2^{1 + 1/4} = 2 \\times 2^{1/4} = 2^{5/4} \\).\n\nWait, but hold on. The four points are on a circle of radius \\( 2^{1/8} \\), but after shifting by \\( -i \\), does that affect the distances? Because shifting doesn't change distances between points, only their positions. So, the polygon remains a square with side length \\( 2^{5/8} \\), so area \\( 2^{5/4} \\).\n\nBut wait, let me double-check. The chord length is \\( 2r \\sin(\\theta/2) \\). Here, \\( \\theta = \\pi/2 \\), so chord length is \\( 2 \\times 2^{1/8} \\times \\sin(\\pi/4) = 2 \\times 2^{1/8} \\times \\sqrt{2}/2 = 2^{1/8} \\times \\sqrt{2} = 2^{1/8 + 1/2} = 2^{5/8} \\). So, chord length is \\( 2^{5/8} \\), so side length is \\( 2^{5/8} \\), area is \\( (2^{5/8})^2 = 2^{5/4} \\).\n\nBut wait, 2^{5/4} is equal to \\( \\sqrt[4]{32} \\), since \\( 32 = 2^5 \\). So, \\( 2^{5/4} = (2^{1/4})^5 \\). Hmm, but the problem says the area can be expressed as \\( p^{a/b} \\), where \\( p \\) is prime. Here, \\( p = 2 \\), \\( a = 5 \\), \\( b = 4 \\). Are 5 and 4 coprime? Yes",
            "ppl": 1.1656439213177796,
            "percentile": 0.755625,
            "accepted": false
        },
        {
            "turn": 8,
            "attempt": 2,
            "model": "draft",
            "output": "1/8} \\), so chord length is \\( 2^{1/8} \\times \\sqrt{2} = 2^{1/8} \\times 2^{1/2} = 2^{5/8} \\).\n\nTherefore, the side length of the square is \\( 2^{5/8} \\), so the area is \\( (2^{5/8})^2 = 2^{5/4} = 2^{1 + 1/4} = 2 \\times 2^{1/4} = 2^{5/4} \\).\n\nWait, but hold on. The four points are on a circle of radius \\( 2^{1/8} \\), but after shifting by \\( -i \\), does that affect the distances? Because shifting doesn't change distances between points, only their positions. So, the polygon remains a square with side length \\( 2^{5/8} \\), so area \\( 2^{5/4} \\).\n\nBut wait, let me double-check. The chord length is \\( 2r \\sin(\\theta/2) \\). Here, \\( \\theta = \\pi/2 \\), so chord length is \\( 2 \\times 2^{1/8} \\times \\sin(\\pi/4) = 2 \\times 2^{1/8} \\times \\sqrt{2}/2 = 2^{1/8} \\times \\sqrt{2} = 2^{1/8 + 1/2} = 2^{5/8} \\). So, chord length is \\( 2^{5/8} \\), so side length is \\( 2^{5/8} \\), area is \\( (2^{5/8})^2 = 2^{5/4} \\).\n\nBut wait, 5/4 is 1.25, so \\( 2^{5/4} = \\sqrt[4]{32} \\). Alternatively, \\( 2^{5/4} = 2^{1 + 1/4} = 2 \\times 2^{1/4} \\).\n\nBut the problem says the area can be expressed as \\( p^{a/b} \\), where \\( p \\) is prime, \\( a \\) and \\( b \\) are coprime. So, 2 is prime, and 5 and",
            "ppl": 1.1623341143624444,
            "percentile": 0.728125,
            "accepted": false
        },
        {
            "turn": 9,
            "attempt": 0,
            "model": "draft",
            "output": " 4 are coprime. So, \\( p = 2 \\), \\( a = 5 \\), \\( b = 4 \\). Therefore, \\( a + b + p = 5 + 4 + 2 = 11 \\).\n\nWait, but hold on. Is the polygon actually a square? Because the roots are equally spaced on the circle, so yes, they form a regular quadrilateral, which is a square. So, the area is indeed \\( 2^{5/4} \\), so the answer is 11.\n\nBut let me just make sure I didn't make a mistake in the substitution.\n\nWe had \\( w = z + i \\), so \\( z = w - i \\). The equation became \\( w^4 = 1 + i \\). So, the four roots of \\( w \\) are the fourth roots of \\( 1 + i \\), which is \\( \\sqrt{2} e^{i\\pi/4} \\). So, the magnitude is \\( (2)^{1/4} \\), but wait, no: \\( (1 + i) \\) has magnitude \\( \\sqrt{2} \\), so the fourth roots have magnitude \\( (\\sqrt{2})^{1/4} = 2^{1/8} \\). So, the radius is \\( 2^{1/8} \\), correct.\n\nTherefore, the chord length is \\( 2 \\times 2^{1/8} \\times \\sin(\\pi/4) = 2^{5/8} \\), so area is \\( (2^{5/8})^2 = 2^{5/4} \\). So, yes, that's correct.\n\nTherefore, the area is \\( 2^{5/4} \\), so \\( a = 5 \\), \\( b = 4 \\), \\( p = 2 \\), so \\( a + b + p = 11 \\).\n\n**Final Answer**\n\\boxed{11}\n</think>\n\nThe given equation is \\( z^4 + 4z^3i - 6z^2 - 4zi - i = 0 \\). The solutions to this equation are the vertices of a convex polygon in the complex plane. We need to find the area of this polygon.\n\nFirst, we recognize that the equation can be simplified by substituting \\( w = z + i \\). This substitution transforms the equation into a",
            "ppl": 0.0,
            "percentile": 0.0,
            "accepted": true,
            "accepted_reason": "answer_found"
        }
    ],
    "question": "The solutions of the equation $z^4+4z^3i-6z^2-4zi-i=0$ are the vertices of a convex polygon in the complex plane.  The area of this polygon can be expressed in the form $p^{a/b},$ where $a,$ $b,$ $p$ are positive integers, $p$ is prime, and $a$ and $b$ are relatively prime.  Find $a + b + p.$"
}