{
    "problem_index": 529,
    "final_answer": "90",
    "duration_seconds": 394.76036977767944,
    "full_history": [
        {
            "turn": 0,
            "attempt": 0,
            "model": "draft",
            "output": "First, I need to determine the total number of possible orders Yann and Camille can make without any restrictions.\n\nSince there are 10 dishes on the menu and each person can choose any dish, Yann has 10 options. For each of Yann's choices, Camille also has 10 options. This means the total number of possible combinations is 10 multiplied by 10, which equals 100.\n\nHowever, the problem states that they refuse to order the same dish. This means we need to subtract the scenarios where both Yann and Camille have chosen the same dish.\n\nThere are 10 dishes, and for each dish, there is exactly one combination where both choose that dish. Therefore, there are 10 such unwanted combinations.\n\nTo find the number of valid combinations where they order different dishes, I subtract the 10 unwanted combinations from the total of 100, resulting in 90.\n\nThus, there are 90 different combinations of meals Yann and Camille can order without ordering the same dish.\n</think>\n\nLet's analyze the problem step by step.\n\n**Problem:**  \nYann and Camille go to a restaurant. There are 10 items on the menu. Each orders one dish. How many different combinations of meals can Yann and Camille order if they refuse to order the same dish? \n\n**Solution:**\n\n1. **Total Possible Orders Without Restrictions:**  \n   - Yann has 10 choices of dishes.  \n   - For each of Yann's choices, Camille also has 10 choices.  \n   - **Total combinations:** \\( 10 \\times 10 = 100 \\).\n\n2. **Subtracting the Cases Where They Order the Same Dish:**  \n   - There are 10 dishes.  \n   - For each dish, there is exactly 1 combination where both Yann and Camille order that dish.  \n   - **Unwanted combinations:** \\( 10 \\).\n\n3. **Calculating Valid Combinations:**  \n   - **Valid combinations:** \\( 100 - 10 = 90 \\).\n\n**Final Answer:**  \n\\(\\boxed{90}\\)",
            "ppl": 1.2238798628312269,
            "percentile": 0.0,
            "accepted": true,
            "accepted_reason": "answer_found"
        }
    ],
    "question": "Yann and Camille go to a restaurant.  If there are 10 items on the menu, and each orders one dish, how many different combinations of meals can Yann and Camille order if they refuse to order the same dish? (It does matter who orders what---Yann ordering chicken and Camille ordering fish is different from Yann ordering fish and Camille ordering chicken.)",
    "ppl_history": [
        1.2238798628312269
    ],
    "avg_ppl": 1.2238798628312269
}