{
    "problem_index": 550,
    "final_answer": "6.0",
    "duration_seconds": 4.843759775161743,
    "full_history": [
        {
            "turn": 0,
            "model": "draft",
            "output": "To determine the average price per stamp in the 70s, I need to calculate the total cost of all 70s stamps and divide it by the total number of 70s stamps Juan owns.\n\nFirst, I'll identify the prices for each country in the 70s:\n- Brazil: 6 cents\n- France: 6 cents\n- Peru: 6 cents\n- Spain: 6 cents\n\nNext, I'll determine the number of stamps for each country:\n- Brazil: 12 stamps\n- France: 12 stamps\n- Peru: 12 stamps\n- Spain: 12 stamps\n\nSince all countries have the same price in the 70s, the total number of 70s stamps is 4 countries multiplied by 12 stamps each, resulting in 48 stamps.\n\nThe total cost for all 70s stamps is 48 stamps multiplied by 6 cents per stamp, totaling 288 cents.\n\nFinally, I'll calculate the average price by dividing the total cost by the total number of stamps: 288 cents divided by 48 stamps equals 6.0 cents per stamp.\n\nTherefore, the average price of Juan's 70s stamps is 6.0 cents.\n</think>\n\n**Solution:**\n\n**Step 1: Understand the Given Data**\n\nFrom the chart, we can see the following information about Juan's stamps:\n\n- **Countries:** Brazil, France, Peru, Spain\n- **Decade:** 50s, 60s, 70s, 80s\n- **Prices (in cents):**\n  - Brazil: 6 cents\n  - France: 6 cents\n  - Peru: 4 cents\n  - Spain: 5 cents\n\n**Step 2: Extract Relevant Data for the 70s**\n\nFor the **70s** (which we assume corresponds to the 1970s), the prices of the stamps are:\n\n- **Brazil:** 6 cents\n- **France:** 6 cents\n- **Peru:** 6 cents\n- **Spain:** 6 cents\n\n**Step 3: Determine the Number of Stamps in the 70s**\n\nFrom the chart, in the 70s:\n\n- **Brazil:** 12 stamps\n- **France:** 12 stamps\n- **Peru:** 12 stamps\n- **Spain:** 12 stamps\n\nTotal number of 70s stamps:\n\\[ 12 + 12 + 12 +"
        },
        {
            "turn": 0,
            "model": "self_ppl",
            "ppl": 1.265368384932586,
            "percentile": 0.968125
        },
        {
            "turn": 0,
            "model": "self_continue",
            "output": " 12 = 48 \\text{ stamps} \\]\n\n**Step 4: Calculate the Total Cost of 70s Stamps**\n\nTotal cost for 70s stamps:\n\\[ 48 \\text{ stamps} \\times 6 \\text{ cents/stamp} = 288 \\text{ cents} \\]\n\n**Step 5: Compute the Average Price per 70s Stamp**\n\nAverage price:\n\\[ \\frac{288 \\text{ cents}}{48 \\text{ stamps}} = 6.0 \\text{ cents/stamp} \\]\n\n**Final Answer:**\n\n\\boxed{6.0}"
        }
    ],
    "question": "$\\textbf{Juan's Old Stamping Grounds}$\n\nJuan organizes the stamps in his collection by country and by the decade in which they were issued. The prices he paid for them at a stamp shop were: Brazil and France, $6$ cents each, Peru $4$ cents each, and Spain $5$ cents each. (Brazil and Peru are South American countries and France and Spain are in Europe.) [asy]\n/* AMC8 2002 #8, 9, 10 Problem */\nsize(3inch, 1.5inch);\nfor ( int y = 0; y <= 5; ++y )\n{\n\ndraw((0,y)--(18,y));\n}\ndraw((0,0)--(0,5));\ndraw((6,0)--(6,5));\ndraw((9,0)--(9,5));\ndraw((12,0)--(12,5));\ndraw((15,0)--(15,5));\ndraw((18,0)--(18,5));\n\nlabel(scale(0.8)*\"50s\", (7.5,4.5));\nlabel(scale(0.8)*\"4\", (7.5,3.5));\nlabel(scale(0.8)*\"8\", (7.5,2.5));\nlabel(scale(0.8)*\"6\", (7.5,1.5));\nlabel(scale(0.8)*\"3\", (7.5,0.5));\n\nlabel(scale(0.8)*\"60s\", (10.5,4.5));\nlabel(scale(0.8)*\"7\", (10.5,3.5));\nlabel(scale(0.8)*\"4\", (10.5,2.5));\nlabel(scale(0.8)*\"4\", (10.5,1.5));\nlabel(scale(0.8)*\"9\", (10.5,0.5));\n\nlabel(scale(0.8)*\"70s\", (13.5,4.5));\nlabel(scale(0.8)*\"12\", (13.5,3.5));\nlabel(scale(0.8)*\"12\", (13.5,2.5));\nlabel(scale(0.8)*\"6\", (13.5,1.5));\nlabel(scale(0.8)*\"13\", (13.5,0.5));\n\nlabel(scale(0.8)*\"80s\", (16.5,4.5));\nlabel(scale(0.8)*\"8\", (16.5,3.5));\nlabel(scale(0.8)*\"15\", (16.5,2.5));\nlabel(scale(0.8)*\"10\", (16.5,1.5));\nlabel(scale(0.8)*\"9\", (16.5,0.5));\n\nlabel(scale(0.8)*\"Country\", (3,4.5));\nlabel(scale(0.8)*\"Brazil\", (3,3.5));\nlabel(scale(0.8)*\"France\", (3,2.5));\nlabel(scale(0.8)*\"Peru\", (3,1.5));\nlabel(scale(0.8)*\"Spain\", (3,0.5));\n\nlabel(scale(0.9)*\"Juan's Stamp Collection\", (9,0), S);\nlabel(scale(0.9)*\"Number of Stamps by Decade\", (9,5), N);\n[/asy] What was the average price, in cents, of his $70\\text{'s}$ stamps? Round your answer to the nearest tenth of a cent."
}